mtdatasdk/__init__.py
mtdatasdk/api.py
mtdatasdk/calendar_service.py
mtdatasdk/client.py
mtdatasdk/finance_service.py
mtdatasdk/finance_tables.py
mtdatasdk/fundamentals_tables_gen.py
mtdatasdk/mtdata.thrift
mtdatasdk/table.py
mtdatasdk/utils.py
mtdatasdk-1.0.2.dist-info/LICENSE
mtdatasdk-1.0.2.dist-info/METADATA
mtdatasdk-1.0.2.dist-info/WHEEL
mtdatasdk-1.0.2.dist-info/top_level.txt
mtdatasdk-1.0.2.dist-info/RECORD
